kfc_2_snow/__init__.py
kfc_2_snow/cli.py
kfc_2_snow/helpers/__init__.py
kfc_2_snow/helpers/json2csv.py
kfc_2_snow/helpers/logging.py
kfc_2_snow/main.py
kfc_2_snow-1.0.3.dist-info/METADATA
kfc_2_snow-1.0.3.dist-info/WHEEL
kfc_2_snow-1.0.3.dist-info/entry_points.txt
kfc_2_snow-1.0.3.dist-info/RECORD
