Metadata-Version: 2.1
Name: kfc-2-snow
Version: 1.0.3
Summary: 
Author: sbailey
Author-email: 1661003+spbsoluble@users.noreply.github.com
Requires-Python: >=3.8
Classifier: Programming Language :: Python :: 3
Classifier: Programming Language :: Python :: 3.8
Classifier: Programming Language :: Python :: 3.9
Classifier: Programming Language :: Python :: 3.10
Classifier: Programming Language :: Python :: 3.11
Classifier: Programming Language :: Python :: 3.12
Requires-Dist: click
Requires-Dist: keyfactor-command-sdk (>=11.0.0a0,<12.0.0)
Requires-Dist: requests
